extras/__init__.py
PyEmbedding-0.0.1.dist-info/METADATA
PyEmbedding-0.0.1.dist-info/WHEEL
PyEmbedding-0.0.1.dist-info/top_level.txt
PyEmbedding-0.0.1.dist-info/RECORD
